igs_core/__init__.py
igs_core/aws/__init__.py
igs_core/aws/batch.py
igs_core/aws/glue.py
igs_core/aws/s3.py
igs_core/aws/ssm.py
igs_core/benchmarking/__init__.py
igs_core/benchmarking/display_usage.py
igs_core/benchmarking/worker_class.py
igs_core/exceptions/__init__.py
igs_core/exceptions/intelligentsales_infra_exceptions.py
igs_core/local_stack/__init__.py
igs_core/local_stack/boto_client_moks/__init__.py
igs_core/local_stack/boto_client_moks/localstack_clients.py
igs_core/local_stack/container_manager/__init__.py
igs_core/local_stack/container_manager/db_container.py
igs_core/local_stack/container_manager/localstack_container.py
igs_core/local_stack/set_up/__init__.py
igs_core/local_stack/set_up/config.py
igs_core/local_stack/set_up/context.py
igs_core/local_stack/set_up/event_factory.py
igs_core/local_stack/set_up/infrastructure.py
igs_core/local_stack/set_up/module_loader.py
igs_core/logger/__init__.py
igs_core/logger/intelligentsales_logger.py
igs_core/singleton_metaclass/__init__.py
igs_core/singleton_metaclass/singleton.py
intelligent_sales_core-1.0.15.dist-info/LICENSE
intelligent_sales_core-1.0.15.dist-info/METADATA
intelligent_sales_core-1.0.15.dist-info/WHEEL
intelligent_sales_core-1.0.15.dist-info/top_level.txt
intelligent_sales_core-1.0.15.dist-info/RECORD
