Metadata-Version: 2.1
Name: intelligent-sales-core
Version: 1.0.15
Summary: Globally shared modules in all Intelligent-Sales
Author-email: Marc Vea <marc.vea@code.seat>
Project-URL: Homepage, https://pypi.org/project/intelligent-sales-core/
Project-URL: GitHub, https://github.com/seatcode/intelligentsales-core
Classifier: Programming Language :: Python :: 3.9
Classifier: License :: OSI Approved :: GNU General Public License v3 (GPLv3)
Classifier: Operating System :: OS Independent
Classifier: Development Status :: 4 - Beta
Requires-Python: >=3.9
License-File: LICENSE
